specdec/__init__.py
specdec/cli.py
specdec/decoder.py
specdec-0.2.0.dist-info/METADATA
specdec-0.2.0.dist-info/WHEEL
specdec-0.2.0.dist-info/entry_points.txt
specdec-0.2.0.dist-info/top_level.txt
specdec-0.2.0.dist-info/RECORD
