Metadata-Version: 2.4
Name: specdec
Version: 0.2.0
Summary: Speculative Decoder
Author-email: nooralnetz <cneuralnets@gmail.com>
Project-URL: Homepage, https://github.com/
Classifier: Programming Language :: Python :: 3
Classifier: License :: OSI Approved :: MIT License
Classifier: Operating System :: OS Independent
Requires-Python: >=3.9
Requires-Dist: torch
Requires-Dist: transformers
Requires-Dist: numpy
Requires-Dist: matplotlib
